[{"id":87627156,"firstName":"Gladyce","lastName":"McLaughlin","age":126,"address":{"streetAddress":"555 Wintheiser Plains","city":"Adamston","state":"Delaware","postalCode":"47740"},"phoneNumber":[{"type":"amet eu","number":"id"},{"type":"laborum do nostrud","number":"irure qui nulla sed laborum"},{"type":"quis","number":"ut adipisicing"},{"type":"aliqua enim dolor mollit","number":"id"}]},{"id":2014067,"firstName":"William","lastName":"Hodkiewicz","age":10,"address":{"streetAddress":"2242 Ryan Highway","city":"Evechester","state":"Minnesota","postalCode":"06907-8770"},"phoneNumber":[{"type":"dolor dolor nulla","number":"pariatur sunt"},{"type":"in ipsum dolor in","number":"consectetur"}]},{"id":62509292,"firstName":"Leland","lastName":"Orn","age":43,"address":{"streetAddress":"725 Finn Groves","city":"East Sarinastad","state":"Massachusetts","postalCode":"98291"},"phoneNumber":[{"type":"elit in adipisicing","number":"ad velit amet"}]},{"id":-81657720,"firstName":"Brock","lastName":"Wyman","age":33,"address":{"streetAddress":"4354 Giles Throughway","city":"Aleenstad","state":"Minnesota","postalCode":"59778"},"phoneNumber":[{"type":"Ut","number":"fugiat culpa incididunt sunt"}]},{"id":-64565521,"firstName":"Bettye","lastName":"Koepp","age":96,"address":{"streetAddress":"521 Mueller Dam","city":"South Brent","state":"Kentucky","postalCode":"52675-0529"},"phoneNumber":[{"type":"reprehenderit veniam","number":"ad laboris nisi"},{"type":"adipisicing et in culpa","number":"et"},{"type":"incididunt qui deserunt","number":"exercitation ullamco"},{"type":"labore e","number":"dolore"}]},{"id":83198370,"firstName":"Scottie","lastName":"Kreiger","age":129,"address":{"streetAddress":"6066 Abbott Point","city":"Keventon","state":"Texas","postalCode":"08618"},"phoneNumber":[{"type":"aliquip nulla in esse","number":"commodo nisi magna dolor"},{"type":"eiusmod","number":"ut sit pariatur"},{"type":"do","number":"est"},{"type":"tempor","number":"fugiat labore nostrud"}]},{"id":91486448,"firstName":"Arvid","lastName":"Daniel","age":101,"address":{"streetAddress":"3887 Rocio Plains","city":"Bruenborough","state":"Texas","postalCode":"67528"},"phoneNumber":[{"type":"aliqua","number":"ut"},{"type":"aliqua","number":"sint commodo nisi"},{"type":"laborum dolor id ullamco","number":"veniam officia"}]},{"id":29067591,"firstName":"Ryley","lastName":"Torphy","age":46,"address":{"streetAddress":"2933 Jacquelyn Cove","city":"Elyssabury","state":"Alabama","postalCode":"38354-7040"},"phoneNumber":[{"type":"commod","number":"eu ipsum"}]},{"id":80242948,"firstName":"Golda","lastName":"Mertz","age":83,"address":{"streetAddress":"69060 Jalen Lights","city":"Lake Makennaborough","state":"North Dakota","postalCode":"67984-3151"},"phoneNumber":[{"type":"in","number":"quis exercitation"}]},{"id":87944761,"firstName":"Orion","lastName":"Koelpin","age":131,"address":{"streetAddress":"24492 Dicki Light","city":"East Dahliaside","state":"Pennsylvania","postalCode":"26647"},"phoneNumber":[{"type":"pariatur p","number":"sed consectetur"},{"type":"et qui in incididunt enim","number":"occaecat sed irure dolore voluptate"},{"type":"dolore in aliquip","number":"culpa"},{"type":"sed","number":"amet officia ullamco exercitat"},{"type":"esse est ","number":"sit consectetur Duis dolor proident"}]}]s":{"streetAddress":"677 Amari Motorway","city":"Kleinport","state":"Montana","postalCode":"59931"},"phoneNumber":[{"type":"pariatur","number":"Excepteur"},{"type":"sint","number":"est aliquip sed eu ipsum"}]},{"id":-49818282,"firstName":"Valentina","lastName":"Grimes","age":68,"address":{"streetAddress":"83504 Toy Prairie","city":"Streichview","state":"Arkansas","postalCode":"82303"},"phoneNumber":[{"type":"magna ullamco Ut","number":"nisi sit fugiat"}]}]